scandocs/__init__.py
scandocs/documentation/__init__.py
scandocs/documentation/configuration.py
scandocs/documentation/documentation.py
scandocs/documentation/markers.py
scandocs/documentation/replacement.py
scandocs/documentation/themes.py
scandocs/structures/__init__.py
scandocs/structures/class_.py
scandocs/structures/deprecation.py
scandocs/structures/docstring.py
scandocs/structures/error.py
scandocs/structures/module.py
scandocs/structures/package.py
scandocs/structures/parameter.py
scandocs/structures/searchable_structure.py
scandocs/structures/serialized.py
scandocs/structures/signature_structure.py
scandocs/structures/source_structure.py
scandocs/structures/structure.py
scandocs/structures/subroutine.py
scandocs/structures/subroutine_return.py
scandocs/structures/variable.py
scandocs/tags/__init__.py
scandocs/tags/data_tag.py
scandocs/tags/tag.py
scandocs/tags/tags.py
scandocs/templates/lib/components/blocks/ChildBlock.svelte
scandocs/templates/lib/components/blocks/DeprecationBlock.svelte
scandocs/templates/lib/components/blocks/DescriptionBlock.svelte
scandocs/templates/lib/components/blocks/ExamplesBlock.svelte
scandocs/templates/lib/components/blocks/LinksBlock.svelte
scandocs/templates/lib/components/blocks/NotesBlock.svelte
scandocs/templates/lib/components/blocks/ParametersBlock.svelte
scandocs/templates/lib/components/blocks/RaisesBlock.svelte
scandocs/templates/lib/components/blocks/ReturnsBlock.svelte
scandocs/templates/lib/components/blocks/SourceBlock.svelte
scandocs/templates/lib/components/blocks/VariablesBlock.svelte
scandocs/templates/lib/components/extra/Badge.svelte
scandocs/templates/lib/components/navigation/ProjectTree.svelte
scandocs/templates/lib/components/navigation/Search.svelte
scandocs/templates/lib/components/navigation/SearchResult.svelte
scandocs/templates/lib/components/navigation/Sidebar.svelte
scandocs/templates/lib/components/navigation/SmallHeader.svelte
scandocs/templates/lib/components/structures/Class.svelte
ScanDocs-0.1.3.dist-info/LICENSE
ScanDocs-0.1.3.dist-info/METADATA
ScanDocs-0.1.3.dist-info/WHEEL
ScanDocs-0.1.3.dist-info/top_level.txt
ScanDocs-0.1.3.dist-info/RECORD
