Metadata-Version: 2.1
Name: ScanDocs
Version: 0.1.3
Summary: Automatically generate documentation for Python projects
Author-email: Kieran Lock <kieran.lock@outlook.com>
License: GNU GENERAL PUBLIC LICENSE
Project-URL: GitHub, https://github.com/Kieran-Lock/ScanDocs
Project-URL: Documentation, https://scandocs-documentation.vercel.app/
Project-URL: License, https://github.com/Kieran-Lock/ScanDocs/blob/main/LICENSE
Keywords: python,documentation,automation,automatic-documentation,sveltekit
Classifier: Development Status :: 3 - Alpha
Classifier: License :: OSI Approved :: GNU General Public License v3 (GPLv3)
Classifier: Programming Language :: Python :: 3.8
Classifier: Intended Audience :: Developers
Requires-Python: >=3.8
License-File: LICENSE
Requires-Dist: docstring-parser ==0.15
